README.rst
setup.py
magneturi/__init__.py
magneturi/__main__.py
magneturi/bencode.py
magneturi.egg-info/PKG-INFO
magneturi.egg-info/SOURCES.txt
magneturi.egg-info/dependency_links.txt
magneturi.egg-info/entry_points.txt
magneturi.egg-info/top_level.txt