Metadata-Version: 1.0
Name: magneturi
Version: 1.3
Summary: generate bittorrent magnet URI from torrent files
Home-page: https://github.com/thomasleveil/magneturi
Author: Thomas LÉVEIL
Author-email: thomasleveil@gmail.com
License: WTFPL
Platform: UNKNOWN
